df_magic_openSARlab/__init__.py
df_magic_openSARlab/df_magic_openSARlab.py
df_magic_openSARlab-0.0.2.dist-info/LICENSE
df_magic_openSARlab-0.0.2.dist-info/METADATA
df_magic_openSARlab-0.0.2.dist-info/WHEEL
df_magic_openSARlab-0.0.2.dist-info/top_level.txt
df_magic_openSARlab-0.0.2.dist-info/RECORD
