Metadata-Version: 2.1
Name: df-magic-openSARlab
Version: 0.0.2
Summary: Magic commands to get file usage from python function shutil.disk_usage().
Home-page: https://github.com/ASFOpenSARlab/opensarlab-cluster/blob/main/opensarlab/jupyterhub/singleuser/custom_magics/00-df.py
Author: ASF OpenSARlab
Author-email: "OpenSAR Team" <uaf-jupyterhub-asf@alaska.edu>
License: BSD 3-Clause License
Platform: UNKNOWN
Classifier: Programming Language :: Python :: 3
Classifier: Programming Language :: Python :: 3.5
Classifier: Programming Language :: Python :: 3.6
Classifier: Programming Language :: Python :: 3.7
Classifier: Programming Language :: Python :: 3.8
Classifier: Programming Language :: Python :: 3.9
Classifier: License :: OSI Approved :: BSD License
Classifier: Framework :: Jupyter
Classifier: Framework :: Jupyter :: JupyterLab
Classifier: Framework :: Jupyter :: JupyterLab :: 3
Requires-Python: >=3.6
License-File: LICENSE
Requires-Dist: ipython
